typedparser/__init__.py
typedparser/_typedparser.py
typedparser/custom_format.py
typedparser/funcs.py
typedparser/import_from_source_copy.py
typedparser/objects.py
typedparser/typedattr.py
typedparser-0.33.13.dist-info/licenses/LICENSE
typedparser-0.33.13.dist-info/METADATA
typedparser-0.33.13.dist-info/WHEEL
typedparser-0.33.13.dist-info/top_level.txt
typedparser-0.33.13.dist-info/zip-safe
typedparser-0.33.13.dist-info/RECORD
