Metadata-Version: 2.4
Name: typedparser
Version: 0.33.13
Summary: Extension for python argparse with typehints and typechecks.
Author: simon-ging
License: Apache-2.0
Project-URL: Project-URL, https://github.com/simon-ging/typedparser
Keywords: attrs,typing,dict,attr
Platform: any
Classifier: Development Status :: 3 - Alpha
Classifier: Intended Audience :: Developers
Classifier: License :: OSI Approved :: Apache Software License
Classifier: Natural Language :: English
Classifier: Programming Language :: Python :: 3.8
Classifier: Programming Language :: Python :: 3.9
Classifier: Programming Language :: Python :: 3.10
Classifier: Programming Language :: Python :: 3.11
Classifier: Programming Language :: Python :: 3.12
Classifier: Operating System :: OS Independent
Classifier: Topic :: Software Development :: Version Control :: Git
Requires-Python: >=3.8
License-File: LICENSE
Requires-Dist: attrs
Provides-Extra: full
Requires-Dist: numpy; extra == "full"
Dynamic: license-file
